setup.cfg
setup.py
wethepeople/__init__.py
wethepeople/objects.py
wethepeople/url.py
wethepeople.egg-info/PKG-INFO
wethepeople.egg-info/SOURCES.txt
wethepeople.egg-info/dependency_links.txt
wethepeople.egg-info/requires.txt
wethepeople.egg-info/top_level.txt
wethepeople/core/__init__.py
wethepeople/core/exceptions.py
wethepeople/core/url.py