Metadata-Version: 1.1
Name: wethepeople
Version: 0.0.0.1
Summary: We the People api wrapper for python
Home-page: https://github.com/Dolphman/wethepeople
Author: Joshua Walters
Author-email: therealdolphman@gmail.com
License: MIT
Keywords: We The People,api wrapper,api,We the People API,We The People API Wrapper,Wrapper,We The People Api python bindings,web api,web wrapper
Platform: UNKNOWN
Classifier: License :: OSI Approved :: MIT License
Classifier: Operating System :: OS Independent
Classifier: Topic :: Utilities
Classifier: Programming Language :: Python :: 2.7
Classifier: Programming Language :: Python :: 3
Classifier: Programming Language :: Python :: 3.0
Classifier: Programming Language :: Python :: 3.1
Classifier: Programming Language :: Python :: 3.2
Classifier: Programming Language :: Python :: 3.3
Classifier: Programming Language :: Python :: 3.4
Classifier: Programming Language :: Python :: 3.5
